hfortix_fortios
