Metadata-Version: 2.4
Name: hfortix-fortios
Version: 0.5.148
Summary: FortiOS SDK - Part of HFortix
Author-email: "Herman W. Jacobsen" <herman@wjacobsen.fo>
License: Proprietary
Project-URL: Homepage, https://github.com/hermanwjacobsen/hfortix
Project-URL: Repository, https://github.com/hermanwjacobsen/hfortix
Keywords: fortinet,fortigate,fortios,firewall,api,sdk
Classifier: Development Status :: 4 - Beta
Classifier: Intended Audience :: Developers
Classifier: Programming Language :: Python :: 3
Classifier: Programming Language :: Python :: 3.10
Classifier: Programming Language :: Python :: 3.11
Classifier: Programming Language :: Python :: 3.12
Requires-Python: >=3.10
Requires-Dist: hfortix-core>=0.5.148
Requires-Dist: hfortix>=0.5.148
Requires-Dist: pydantic>=2.0
Requires-Dist: httpx>=0.24.0
Provides-Extra: minimal
